keystroke_sim/__init__.py
keystroke_sim/cli.py
keystroke_sim/keyboard_monitor.py
keystroke_sim/logger.py
keystroke_sim/security_analyzer.py
keystroke_sim/simulator.py
keystroke_sim-0.3.0.dist-info/LICENSE
keystroke_sim-0.3.0.dist-info/METADATA
keystroke_sim-0.3.0.dist-info/WHEEL
keystroke_sim-0.3.0.dist-info/entry_points.txt
keystroke_sim-0.3.0.dist-info/top_level.txt
keystroke_sim-0.3.0.dist-info/RECORD
