Metadata-Version: 2.2
Name: keystroke_sim
Version: 0.3.0
Summary: Cross-platform keyboard input simulation and monitoring with security analysis
Author-email: Bassem Abidi <abidi.bassem@me.com>
License: MIT
Project-URL: Homepage, https://github.com/bassemabidi/keystroke_sim
Project-URL: Documentation, https://github.com/bassemabidi/keystroke_sim/blob/main/README.md
Project-URL: Repository, https://github.com/bassemabidi/keystroke_sim.git
Project-URL: Changelog, https://github.com/bassemabidi/keystroke_sim/blob/main/CHANGELOG.md
Keywords: keyboard,automation,monitoring,simulation,input,security,keystroke-dynamics,threat-detection
Classifier: Development Status :: 4 - Beta
Classifier: Intended Audience :: Developers
Classifier: Intended Audience :: Information Technology
Classifier: Intended Audience :: System Administrators
Classifier: License :: OSI Approved :: MIT License
Classifier: Operating System :: OS Independent
Classifier: Programming Language :: Python :: 3
Classifier: Programming Language :: Python :: 3.10
Classifier: Programming Language :: Python :: 3.11
Classifier: Topic :: Software Development :: Testing
Classifier: Topic :: System :: Monitoring
Classifier: Topic :: Security
Classifier: Topic :: System :: Systems Administration :: Authentication/Directory
Requires-Python: >=3.10
License-File: LICENSE
Requires-Dist: keyboard>=0.13.5
Requires-Dist: pynput>=1.7.6
Requires-Dist: pyautogui>=0.9.53
Requires-Dist: cryptography>=41.0.0
Requires-Dist: numpy>=1.21.0
Provides-Extra: dev
Requires-Dist: pytest>=7.0.0; extra == "dev"
Requires-Dist: black>=22.0.0; extra == "dev"
Requires-Dist: isort>=5.0.0; extra == "dev"
Requires-Dist: mypy>=0.900; extra == "dev"
